{
	"info": {
		"_postman_id": "a4206fa0-722f-4f99-ad80-7f41ea483d53",
		"name": "simple-pulumi-crud-collection",
		"schema": "https://schema.getpostman.com/json/collection/v2.1.0/collection.json",
		"_exporter_id": "10907454"
	},
	"item": [
		{
			"name": "get_user",
			"protocolProfileBehavior": {
				"disableBodyPruning": true
			},
			"request": {
				"method": "GET",
				"header": [],
				"body": {
					"mode": "raw",
					"raw": "{\r\n    \"username\" : \"alvin\",\r\n    \"user_id\" : \"1\"\r\n}",
					"options": {
						"raw": {
							"language": "json"
						}
					}
				},
				"url": {
					"raw": "http://127.0.0.1:5000/simple-crud-api/user",
					"protocol": "http",
					"host": [
						"127",
						"0",
						"0",
						"1"
					],
					"port": "5000",
					"path": [
						"simple-crud-api",
						"user"
					]
				}
			},
			"response": []
		},
		{
			"name": "delete_user",
			"request": {
				"method": "DELETE",
				"header": [],
				"body": {
					"mode": "raw",
					"raw": "{\r\n    \"username\" : \"test\",\r\n    \"user_id\": \"1\"\r\n}",
					"options": {
						"raw": {
							"language": "json"
						}
					}
				},
				"url": {
					"raw": "http://127.0.0.1:5000/simple-crud-api/user",
					"protocol": "http",
					"host": [
						"127",
						"0",
						"0",
						"1"
					],
					"port": "5000",
					"path": [
						"simple-crud-api",
						"user"
					]
				}
			},
			"response": []
		},
		{
			"name": "create_user",
			"request": {
				"method": "POST",
				"header": [],
				"body": {
					"mode": "raw",
					"raw": "{\r\n    \"username\" : \"test\",\r\n    \"user_id\": \"1\",\r\n    \"status\" : \"ACTIVE\"\r\n}",
					"options": {
						"raw": {
							"language": "json"
						}
					}
				},
				"url": {
					"raw": "http://127.0.0.1:5000/simple-crud-api/user",
					"protocol": "http",
					"host": [
						"127",
						"0",
						"0",
						"1"
					],
					"port": "5000",
					"path": [
						"simple-crud-api",
						"user"
					]
				}
			},
			"response": []
		},
		{
			"name": "update_user",
			"request": {
				"method": "PUT",
				"header": [],
				"body": {
					"mode": "raw",
					"raw": "{\r\n    \"username\" : \"test\",\r\n    \"user_id\": \"1\",\r\n    \"status\" : \"INACTIVE\"\r\n}",
					"options": {
						"raw": {
							"language": "json"
						}
					}
				},
				"url": {
					"raw": "http://127.0.0.1:5000/simple-crud-api/user",
					"protocol": "http",
					"host": [
						"127",
						"0",
						"0",
						"1"
					],
					"port": "5000",
					"path": [
						"simple-crud-api",
						"user"
					]
				}
			},
			"response": []
		},
		{
			"name": "query_index",
			"protocolProfileBehavior": {
				"disableBodyPruning": true
			},
			"request": {
				"method": "GET",
				"header": [],
				"body": {
					"mode": "raw",
					"raw": "{\r\n    \"status\" : \"INACTIVE\"\r\n}",
					"options": {
						"raw": {
							"language": "json"
						}
					}
				},
				"url": {
					"raw": "http://127.0.0.1:5000/simple-crud-api/user/index",
					"protocol": "http",
					"host": [
						"127",
						"0",
						"0",
						"1"
					],
					"port": "5000",
					"path": [
						"simple-crud-api",
						"user",
						"index"
					]
				}
			},
			"response": []
		}
	]
}